clipd/__init__.py
clipd/__main__.py
clipd/main.py
clipd/base/__init__.py
clipd/base/base.py
clipd/base/check.py
clipd/base/connect.py
clipd/base/describe.py
clipd/base/disconnect.py
clipd/base/eggs.py
clipd/base/export.py
clipd/base/init.py
clipd/base/log.py
clipd/commands/__init__.py
clipd/core/__init__.py
clipd/core/decorators.py
clipd/core/exceptions.py
clipd/core/export.py
clipd/core/load.py
clipd/core/log_utils.py
clipd/core/session.py
clipd/core/suggestions.py
clipd/core/table.py
clipd/ml/__init__.py
clipd/pipelines/__init__.py
clipd/version_control/__init__.py
tests/__init__.py
tests/test_connect.py
tests/test_init.py
clipd-0.1.5.dist-info/METADATA
clipd-0.1.5.dist-info/WHEEL
clipd-0.1.5.dist-info/entry_points.txt
clipd-0.1.5.dist-info/top_level.txt
clipd-0.1.5.dist-info/RECORD
