Metadata-Version: 2.4
Name: clipd
Version: 0.1.5
Home-page: https://github.com/SuzanTurner/clipd
Author: Yadhnika Wakde
Author-email: yadhnikawakde@gmail.com
Project-URL: Bug Tracker, https://github.com/SuzanTurner/clipd/issues
Project-URL: Documentation, https://github.com/SuzanTurner/clipd#readme
Classifier: Programming Language :: Python :: 3
Classifier: License :: OSI Approved :: MIT License
Classifier: Operating System :: OS Independent
Classifier: Environment :: Console
Classifier: Topic :: Utilities
Requires-Python: >=3.8
Requires-Dist: typer[all]
Requires-Dist: pandas
Requires-Dist: scipy
Dynamic: author
Dynamic: author-email
Dynamic: classifier
Dynamic: description
Dynamic: description-content-type
Dynamic: home-page
Dynamic: project-url
Dynamic: requires-dist
Dynamic: requires-python
